{
    "display": {
        "icon": {
            "item": "avp:helm.celtic"
        },
        "title": {
            "translate": "avp.advancements.predators.acquire.biomask.title"
        },
        "description": {
            "translate": "avp.advancements.predators.acquire.biomask.description"
        }
    },
    "parent": "avp:predators/root",
    "criteria": {
        "get_stone": {
            "trigger": "minecraft:inventory_changed",
            "conditions": {
                "items": [
                    {
                        "item": "avp:helm.celtic"
                    }
                ]
            }
        }
    }
}